tree2fs/__init__.py
tree2fs/__version__.py
tree2fs/exceptions.py
tree2fs/builder/__init__.py
tree2fs/builder/fs_builder.py
tree2fs/cli/__init__.py
tree2fs/cli/main.py
tree2fs/models/__init__.py
tree2fs/models/file_item.py
tree2fs/models/node.py
tree2fs/parser/__init__.py
tree2fs/parser/parser.py
tree2fs-0.1.0.dist-info/licenses/LICENSE
tree2fs-0.1.0.dist-info/METADATA
tree2fs-0.1.0.dist-info/WHEEL
tree2fs-0.1.0.dist-info/entry_points.txt
tree2fs-0.1.0.dist-info/top_level.txt
tree2fs-0.1.0.dist-info/RECORD
