Metadata-Version: 2.4
Name: tree2fs
Version: 0.1.0
Summary: Convert tree-formatted text into filesystem structures
Author-email: Abdellah HALLOU <abdeallahhallou33@gmail.com>
License: MIT
Project-URL: Homepage, https://github.com/ABDELLAH-Hallou/tree2fs
Project-URL: Documentation, https://github.com/ABDELLAH-Hallou/tree2fs#readme
Project-URL: Repository, https://github.com/ABDELLAH-Hallou/tree2fs
Project-URL: Bug Tracker, https://github.com/ABDELLAH-Hallou/tree2fs/issues
Keywords: tree,filesystem,directory,structure,cli,project structure
Classifier: Development Status :: 4 - Beta
Classifier: Intended Audience :: Developers
Classifier: License :: OSI Approved :: MIT License
Classifier: Programming Language :: Python :: 3
Classifier: Programming Language :: Python :: 3.9
Classifier: Programming Language :: Python :: 3.10
Classifier: Programming Language :: Python :: 3.11
Classifier: Programming Language :: Python :: 3.12
Classifier: Topic :: Software Development :: Libraries :: Python Modules
Classifier: Topic :: System :: Filesystems
Classifier: Topic :: Utilities
Requires-Python: >=3.9
License-File: LICENSE
Requires-Dist: pydantic>=2.12.4
Provides-Extra: dev
Requires-Dist: pytest>=7.0; extra == "dev"
Requires-Dist: pytest-cov>=4.0; extra == "dev"
Requires-Dist: black>=23.0; extra == "dev"
Requires-Dist: flake8>=6.0; extra == "dev"
Requires-Dist: mypy>=1.0; extra == "dev"
Requires-Dist: pydantic>=2.12.4; extra == "dev"
Dynamic: license-file
